byzh/core/B_argv.py
byzh/core/B_os.py
byzh/core/__init__.py
byzh/core/__main__.py
byzh/core/Barchive/__init__.py
byzh/core/Barchive/archive.py
byzh/core/Bdownloader/__init__.py
byzh/core/Bdownloader/one.py
byzh/core/Brecorder/__init__.py
byzh/core/Brecorder/record1d.py
byzh/core/Brecorder/record2d.py
byzh/core/Btable/__init__.py
byzh/core/Btable/auto_table.py
byzh/core/Bterminal/__init__.py
byzh/core/Bterminal/cmd.py
byzh/core/Btqdm/__init__.py
byzh/core/Btqdm/my_tqdm.py
byzh/core/Butils/__init__.py
byzh/core/Butils/decorator.py
byzh/core/Butils/text_style.py
byzh/core/Butils/timer.py
byzh/core/Bwriter/__init__.py
byzh/core/Bwriter/writer.py
byzh_core-0.0.9.21.dist-info/LICENSE
byzh_core-0.0.9.21.dist-info/METADATA
byzh_core-0.0.9.21.dist-info/WHEEL
byzh_core-0.0.9.21.dist-info/entry_points.txt
byzh_core-0.0.9.21.dist-info/top_level.txt
byzh_core-0.0.9.21.dist-info/RECORD
