Metadata-Version: 2.1
Name: byzh-core
Version: 0.0.9.21
Summary: byzh-core是byzh系列的核心库，包含了一些常用的工具函数和类。
Author: byzh_rc
License: MIT
License-File: LICENSE
Requires-Dist: wcwidth
